xandroid/__init__.py
xandroid/xmlparser/__init__.py
xandroid/xmlparser/axmlparser.py
xandroid/xmlparser/axmlprinter.py
xandroid/xmlparser/bytecode.py
xandroid/xmlparser/stringblock.py
xandroid/xmlparser/typeconstants.py
xandroid-0.0.1.dist-info/LICENSE.txt
xandroid-0.0.1.dist-info/METADATA
xandroid-0.0.1.dist-info/WHEEL
xandroid-0.0.1.dist-info/top_level.txt
xandroid-0.0.1.dist-info/RECORD
