Metadata-Version: 2.1
Name: xandroid
Version: 0.0.1
Summary: Simple tool Reverse Engineering apk
Author-email: Gekozen <unkwnxc@gmail.com>
Classifier: Programming Language :: Python :: 3
Classifier: License :: OSI Approved :: MIT License
Classifier: Operating System :: OS Independent
Requires-Python: >=3.9
License-File: LICENSE.txt
